secret/SCRATCH.py
secret/__init__.py
shared/__init__.py
shared/__main__.py
shared/const/.private
shared/const/__init__.py
shared/constant/.private
shared/constant/__init__.py
shared/database/.private
shared/database/__init__.py
shared/document/.private
shared/document/__init__.py
shared/document/jesth/__init__.py
shared/document/json/__init__.py
shared/dossier/.private
shared/dossier/__init__.py
shared/dto/__init__.py
shared/error/__init__.py
shared/hooking/__init__.py
shared/hooking/ante_build_hook.py
shared/hooking/ante_release_hook.py
shared/hooking/post_build_hook.py
shared/hooking/post_release_hook.py
shared/misc/__init__.py
shared/pyrustic_data/build_report.json
shared/pyrustic_data/hooking.json
shared/pyrustic_data/hubstore.json
shared/pyrustic_data/release_info.json
shared/pyrustic_data/backstage/config/build.json
shared/pyrustic_data/backstage/config/init.json
shared/pyrustic_data/backstage/config/release.json
shared/pyrustic_data/backstage/data/build_report.json
shared/pyrustic_data/backstage/data/github_release_form.json
shared/pyrustic_data/backstage/hooking/build.json
shared/pyrustic_data/backstage/hooking/init.json
shared/pyrustic_data/backstage/hooking/release.json
shared/pyrustic_data/backstage/report/build_report.json
shared/pyrustic_data/backstage/report/release_report.json
shared/pyrustic_data/hubstore/img.json
shared/pyrustic_data/hubstore/promotion.json
shared/util/.private
shared/util/__init__.py
tests/__init__.py
tests/__main__.py
tests/test_database.py
tests/test_document.py
tests/test_dossier.py
tests/test_misc.py
tests/test_root_imports.py
tests/util/__init__.py
shared-0.0.31.dist-info/LICENSE
shared-0.0.31.dist-info/METADATA
shared-0.0.31.dist-info/WHEEL
shared-0.0.31.dist-info/entry_points.txt
shared-0.0.31.dist-info/top_level.txt
shared-0.0.31.dist-info/RECORD
