Metadata-Version: 2.1
Name: shared
Version: 0.0.31
Summary: Data exchange and persistence based on human-readable files
Home-page: https://github.com/pyrustic/shared
Author: Pyrustic Architect
Author-email: rusticalex@yahoo.com
Maintainer: Pyrustic Architect
Maintainer-email: rusticalex@yahoo.com
License: MIT
Classifier: Programming Language :: Python
Classifier: Programming Language :: Python :: 3
Classifier: License :: OSI Approved :: MIT License
Classifier: Operating System :: OS Independent
Classifier: Intended Audience :: Developers
Classifier: Development Status :: 4 - Beta
Requires-Python: >=3.5
License-File: LICENSE
Requires-Dist: kvf
